rest_framework_api_key/__init__.py
rest_framework_api_key/__version__.py
rest_framework_api_key/admin.py
rest_framework_api_key/apps.py
rest_framework_api_key/crypto.py
rest_framework_api_key/models.py
rest_framework_api_key/permissions.py
rest_framework_api_key/py.typed
rest_framework_api_key/migrations/0001_initial.py
rest_framework_api_key/migrations/0002_auto_20190529_2243.py
rest_framework_api_key/migrations/0003_auto_20190623_1952.py
rest_framework_api_key/migrations/0004_prefix_hashed_key.py
rest_framework_api_key/migrations/__init__.py
djangorestframework_api_key-2.1.0.dist-info/LICENSE
djangorestframework_api_key-2.1.0.dist-info/METADATA
djangorestframework_api_key-2.1.0.dist-info/WHEEL
djangorestframework_api_key-2.1.0.dist-info/top_level.txt
djangorestframework_api_key-2.1.0.dist-info/RECORD
