Metadata-Version: 2.1
Name: djangorestframework-api-key
Version: 2.1.0
Summary: API key permissions for the Django REST Framework
Home-page: http://github.com/florimondmanca/djangorestframework-api-key
Author: Florimond Manca
Author-email: florimond.manca@gmail.com
License: MIT
Project-URL: Documentation, https://florimondmanca.github.io/djangorestframework-api-key/
Platform: UNKNOWN
Classifier: Development Status :: 4 - Beta
Classifier: Operating System :: OS Independent
Classifier: Intended Audience :: Developers
Classifier: Programming Language :: Python :: 3 :: Only
Classifier: Programming Language :: Python :: 3.6
Classifier: Programming Language :: Python :: 3.7
Classifier: Programming Language :: Python :: 3.8
Classifier: Environment :: Web Environment
Classifier: Topic :: Software Development :: Libraries :: Python Modules
Classifier: Framework :: Django
Classifier: Framework :: Django :: 2.2
Classifier: Framework :: Django :: 3.0
Requires-Python: >=3.6
